LICENSE
README.md
setup.py
test/test_df_content.py
traice/Traicer.py
traice/__init__.py
traice.egg-info/PKG-INFO
traice.egg-info/SOURCES.txt
traice.egg-info/dependency_links.txt
traice.egg-info/requires.txt
traice.egg-info/top_level.txt