Metadata-Version: 2.1
Name: traice
Version: 0.1.0
Summary: Tiny yet useful tool for consistent model training logs generation
Home-page: https://github.com/zeionara/traice
Author: Zeio Nara
Author-email: zeionara@gmail.com
Classifier: Programming Language :: Python :: 3.10
License-File: LICENSE
